<?xml version="1.0" encoding="utf-8"?>
<fmg>
<compression>None</compression>
<version>DarkSouls3</version>
<bigendian>False</bigendian>
<entries>
<text id="200000">Наделяет оружие свойствами и навыками</text>
<text id="200100">Наделяет оружие свойствами и навыками</text>
<text id="400000">Наделяет оружие свойствами и навыками</text>
<text id="401000">Наделяет оружие свойствами и навыками</text>
<text id="402000">Наделяет оружие свойствами и навыками</text>
<text id="403000">Наделяет оружие свойствами и навыками</text>
<text id="404000">Наделяет оружие свойствами и навыками</text>
<text id="405000">Наделяет оружие свойствами и навыками</text>
<text id="406000">Наделяет оружие свойствами и навыками</text>
<text id="407000">Наделяет оружие свойствами и навыками</text>
<text id="409000">Наделяет оружие свойствами и навыками</text>
<text id="410000">Наделяет оружие свойствами и навыками</text>
<text id="411000">Наделяет оружие свойствами и навыками</text>
<text id="412000">Наделяет оружие свойствами и навыками</text>
<text id="413000">Наделяет оружие свойствами и навыками</text>
<text id="414000">Наделяет оружие свойствами и навыками</text>
<text id="415000">Наделяет оружие свойствами и навыками</text>
<text id="416000">Наделяет оружие свойствами и навыками</text>
<text id="417000">Наделяет оружие свойствами и навыками</text>
<text id="418000">Наделяет оружие свойствами и навыками</text>
<text id="419000">Наделяет оружие свойствами и навыками</text>
<text id="422000">Наделяет оружие свойствами и навыками</text>
<text id="505000">Наделяет оружие свойствами и навыками</text>
<text id="548000">Наделяет оружие свойствами и навыками</text>
<text id="800000">Наделяет оружие свойствами и навыками</text>
</entries>
</fmg>