<?xml version="1.0" encoding="utf-8"?>
<fmg>
<compression>None</compression>
<version>DarkSouls3</version>
<bigendian>False</bigendian>
<entries>
<text id="3000000">Danes Hut</text>
<text id="3000100">Trockenblatt-Robe</text>
<text id="3000200">Trockenblatt-Armwickel</text>
<text id="3000300">Hohe Trockenblatt-Stiefel</text>
<text id="3001100">Trockenblatt-Robe (Geänd.)</text>
<text id="3010000">Gaius' Helm</text>
<text id="3010100">Gaius' Rüstung</text>
<text id="3010200">Gaius' Stulpen</text>
<text id="3010300">Gaius' Beinschutz</text>
<text id="5000000">Eidesuchender Ritterhelm</text>
<text id="5000100">Ledas Rüstung</text>
<text id="5000200">Eidesuchender Ritterstulpen</text>
<text id="5000300">Eidesuchender Ritterbeinschutz</text>
<text id="5002100">Eidesuchender Ritterrüstung</text>
<text id="5010000">Grünspan-Helm</text>
<text id="5010100">Grünspan-Rüstung</text>
<text id="5010200">Grünspan-Stulpen</text>
<text id="5010300">Grünspan-Beinschutz</text>
<text id="5020000">Ralvas Pelz</text>
<text id="5020100">Eisennieten Rüstung</text>
<text id="5020200">Eisennieten Stulpen</text>
<text id="5020300">Eisennieten Beinschutz</text>
<text id="5021000">Fang Helm</text>
<text id="5030000">Thiolliers Maske</text>
<text id="5030100">Thiolliers Gewand</text>
<text id="5030200">Thiolliers Handschuhe</text>
<text id="5030300">Thiolliers Hose</text>
<text id="5031100">Thiolliers Gewand (Geänd.)</text>
<text id="5060000">Hohepriester-Hut</text>
<text id="5060100">Hohepriester-Robe</text>
<text id="5060200">Hohepriester-Handschuhe</text>
<text id="5060300">Hohepriester-Untergewand</text>
<text id="5062100">Fingerrobe</text>
<text id="5070000">Raupenmaske</text>
<text id="5070100">Geflochtene Cord-Robe</text>
<text id="5070200">Geflochtene Armwickel</text>
<text id="5070300">Beschmutzter Lendenschurz</text>
<text id="5080000">Kapuze einer Tänzerin</text>
<text id="5080100">Kleid einer Tänzerin</text>
<text id="5080200">Armschutz einer Tänzerin</text>
<text id="5080300">Hose einer Tänzerin</text>
<text id="5081100">Kleid einer Tänzerin (Geänd.)</text>
<text id="5090000">Helm der Nacht</text>
<text id="5090100">Rüstung der Nacht</text>
<text id="5090200">Stulpen der Nacht</text>
<text id="5090300">Beinschutz der Nacht</text>
<text id="5100000">Igons Helm</text>
<text id="5100100">Igons Rüstung</text>
<text id="5100200">Igons Stulpen</text>
<text id="5100300">Igons Lendenschurz</text>
<text id="5101000">Igons Helm (Geänd.)</text>
<text id="5101100">Igons Rüstung (Geänd.)</text>
<text id="5110000">Maske des Weisen</text>
<text id="5110100">Ansbachs Kleidung</text>
<text id="5110200">Ansbachs Manschetten</text>
<text id="5110300">Ansbachs Stiefel</text>
<text id="5111100">Ansbachs Kleidung (Geänd.)</text>
<text id="5120000">Freyjas Helm</text>
<text id="5120100">Freyjas Rüstung</text>
<text id="5120200">Freyjas Stulpen</text>
<text id="5120300">Freyjas Beinschutz</text>
<text id="5121100">Freyja Rüstung (Geänd.)</text>
<text id="5130000">Helm der Einsamkeit</text>
<text id="5130100">Rüstung der Einsamkeit</text>
<text id="5130200">Stulpen der Einsamkeit</text>
<text id="5130300">Beinschutz der Einsamkeit</text>
<text id="5131100">Rüstung der Einsamkeit (Geänd.)</text>
<text id="5140000">Messmer-Soldatenhelm</text>
<text id="5140100">Messmer-Soldatenrüstung</text>
<text id="5140200">Messmer-Soldatenstulpen</text>
<text id="5140300">Messmer-Soldatenbeinschutz</text>
<text id="5141100">Messmer-Soldatenrüstung (Geänd.)</text>
<text id="5150000">Helm der Schwarzen Ritter</text>
<text id="5150100">Rüstung der Schwarzen Ritter</text>
<text id="5150200">Stulpen der Schwarzen Ritter</text>
<text id="5150300">Beinschutz der Schwarzen Ritter</text>
<text id="5160000">Rakshasa-Helm</text>
<text id="5160100">Rakshasa-Rüstung</text>
<text id="5160200">Rakshasa-Stulpen</text>
<text id="5160300">Rakshasa-Beinschutz</text>
<text id="5180000">Feuerritter-Helm</text>
<text id="5180100">Feuerritter-Rüstung</text>
<text id="5180200">Feuerritter-Stulpen</text>
<text id="5180300">Feuerritter-Beinschutz</text>
<text id="5181100">Feuerritter-Rüstung (Geänd.)</text>
<text id="5182000">Todesmasken-Helm</text>
<text id="5183000">Geflügelter Schlangenhelm</text>
<text id="5184000">Salzas Kapuze</text>
<text id="5190000">Lederstirnband</text>
<text id="5190100">Glorreiche Kleidung</text>
<text id="5190200">Lederarmwickel</text>
<text id="5190300">Lederbeinwickel</text>
<text id="5191000">Lederhelm</text>
<text id="5191100">Hochlandkleidung</text>
<text id="5200000">Todesritter-Helm</text>
<text id="5200100">Todesritter-Rüstung</text>
<text id="5200200">Todesritter-Stulpen</text>
<text id="5200300">Todesritter-Beinschutz</text>
<text id="5210000">Fluchklingen-Maske</text>
<text id="5210100">Kleidung des Asketen</text>
<text id="5210200">Handgelenksschütze der Asketen</text>
<text id="5210300">Knöchelschützer der Asketen</text>
<text id="5220000">Messmers Helm</text>
<text id="5220100">Messmers Rüstung</text>
<text id="5220200">Messmers Armschutz</text>
<text id="5220300">Messmers Beinschutz</text>
<text id="5221000">Messmers Helm (Geänd.)</text>
<text id="5230000">Grabvogel-Helm</text>
<text id="5230100">Schwarzfeder Grabvogel-Rüstung</text>
<text id="5230200">Grabvogel-Armreife</text>
<text id="5230300">Grabvogel-Fußreife</text>
<text id="5231100">Grabvogel-Rüstung</text>
<text id="5240000">Gewöhnlicher Soldatenhelm</text>
<text id="5240100">Gewöhnliche Soldatenstoffrüstung</text>
<text id="5240200">Gewöhnliche Soldatenstulpen</text>
<text id="5240300">Gewöhnlicher Soldatenbeinschutz</text>
<text id="5250000">Hornkrieger-Helm</text>
<text id="5250100">Hornkrieger-Rüstung</text>
<text id="5250200">Hornkrieger-Armschutz</text>
<text id="5250300">Hornkrieger-Beinschutz</text>
<text id="5252000">Göttlicher Bestienhelm</text>
<text id="5252100">Göttliche Bestienkrieger-Rüstung</text>
<text id="5253000">Göttlicher Vogelhelm</text>
<text id="5253100">Göttliche Vogelkrieger-Rüstung</text>
<text id="5253200">Göttliche Vogelkrieger-Armschutz</text>
<text id="5253300">Göttlicher Vogelkrieger-Beinschutz</text>
<text id="5260000">Rellanas Helm</text>
<text id="5260100">Rellanas Rüstung</text>
<text id="5260200">Rellanas Handschuhe</text>
<text id="5260300">Rellanas Beinschutz</text>
<text id="5270000">Helm des jungen Löwen</text>
<text id="5270100">Rüstung des jungen Löwen</text>
<text id="5270200">Stulpen des jungen Löwen</text>
<text id="5270300">Beinschutz des jungen Löwen</text>
<text id="5271100">Rüstung des jungen Löwen (Geänd.)</text>
<text id="5272000">Kranz des Lichts</text>
<text id="5280000">Helm der Schattenmilizionäre</text>
<text id="5280100">Rüstung der Schattenmilizionäre</text>
<text id="5280200">Handschuhe der Schattenmilizionäre</text>
<text id="5280300">Beinschutz der Schattenmilizionäre</text>
<text id="5290000">Göttlicher Bestienkopf</text>
<text id="5300000">St. Trinas Blüte</text>
<text id="5310000">Hammerhelm des Schmelztiegels</text>
<text id="5320000">Großes Gefäß</text>
<text id="5330000">Wichtkopf (Löwe)</text>
</entries>
</fmg>